lightlyse/BasicClasses.py
lightlyse/__init__.py
lightlyse-0.1.dist-info/LICENSE
lightlyse-0.1.dist-info/METADATA
lightlyse-0.1.dist-info/WHEEL
lightlyse-0.1.dist-info/top_level.txt
lightlyse-0.1.dist-info/RECORD
